setup.cfg
setup.py
muck/__init__.py
muck/__main__.py
muck/constants.py
muck/db.py
muck/paths.py
muck/py_deps.py
muck.egg-info/PKG-INFO
muck.egg-info/SOURCES.txt
muck.egg-info/dependency_links.txt
muck.egg-info/entry_points.txt
muck.egg-info/requires.txt
muck.egg-info/top_level.txt
muck/pithy/__init__.py
muck/pithy/fs.py
muck/pithy/io.py
muck/pithy/json_utils.py
muck/pithy/path_encode.py
muck/pithy/string_utils.py
muck/pithy/task.py
muck/pithy/transform.py