Metadata-Version: 1.1
Name: muck
Version: 0.0.3
Summary: Muck is a build tool for data projects that automatically calculates dependencies.
Home-page: https://github.com/gwk/muck
Author: George King
Author-email: george.w.king@gmail.com
License: CC0
Keywords: build tool,data science
Platform: UNKNOWN
Classifier: Development Status :: 3 - Alpha
Classifier: Environment :: Console
Classifier: Intended Audience :: Developers
Classifier: Intended Audience :: Education
Classifier: Intended Audience :: Information Technology
Classifier: Intended Audience :: Science/Research
Classifier: License :: CC0 1.0 Universal (CC0 1.0) Public Domain Dedication
Classifier: Programming Language :: Python :: 3 :: Only
Classifier: Topic :: Documentation
Classifier: Topic :: Education
Classifier: Topic :: Internet
Classifier: Topic :: Multimedia
Classifier: Topic :: Software Development
Classifier: Topic :: Software Development :: Build Tools
Classifier: Topic :: Software Development :: Documentation
Classifier: Topic :: Text Processing
Classifier: Topic :: Text Processing :: Markup
Classifier: Topic :: Text Processing :: Markup :: HTML
